<?xml version="1.0" encoding="iso-8859-1"?>
<items>
<playlist_name><![CDATA[Videos Y Conciertos]]></playlist_name>
  
  
<channel>
<title><![CDATA[SARATOGA 'Mi Venganza']]></title>
<logo_30x30><![CDATA[]]></logo_30x30>
<description><![CDATA[<img src="" />]]> </description>
<stream_url><![CDATA[http://r2---sn-bvvbax-v8cl.googlevideo.com/videoplayback?upn=uKuV874dB5w&mime=video%2Fmp4&sparams=dur%2Cei%2Cid%2Cinitcwndbps%2Cip%2Cipbits%2Citag%2Clmt%2Cmime%2Cmm%2Cmn%2Cms%2Cmv%2Cnh%2Cpl%2Cratebypass%2Csource%2Cupn%2Cexpire&source=youtube&ip=95.189.102.239&key=yt6&dur=278.058&lmt=1489609124074040&id=o-AAt27B_dWPuBzcI0Bu3HXrOBtr3RXDbBCGV9_KqsBoIF&itag=22&ipbits=0&mn=sn-bvvbax-v8cl&mm=31&ms=au&ei=imkdWdCtM5WxYaOUkegN&mv=m&mt=1495099707&expire=1495121386&initcwndbps=770000&ratebypass=yes&pl=18&nh=EAQ&signature=62F7BA28C273EEEBE213093CF7F30742DCC7B743.5A12EBE8626C07B3D0CE355E60776D2CF97F5ED2&title=SARATOGA+%27Mi+Venganza%27+%28Videoclip%29]]></stream_url>
<video_type>http</video_type>
<buffer_kb>20480</buffer_kb>
</channel>
  
  
  <next_page_url text="CH+ FAVORITOS"><![CDATA[nStreamFavorites.xml]]></next_page_url>
<prev_page_url text="CH- ATRAS"><![CDATA[nStreamVOD.xml]]></prev_page_url>

</items>
